redboxdb/RedBoxServer.exe
redboxdb/__init__.py
redboxdb/client.py
redboxdb-1.0.3.dist-info/METADATA
redboxdb-1.0.3.dist-info/WHEEL
redboxdb-1.0.3.dist-info/top_level.txt
redboxdb-1.0.3.dist-info/RECORD
