Metadata-Version: 2.4
Name: redboxdb
Version: 1.0.3
Summary: Python client for the RedBox Vector Database
Home-page: https://github.com/bibidhSubedi0/RedBoxDb
Author: Bibidh Subedi
Classifier: Programming Language :: Python :: 3
Classifier: License :: OSI Approved :: MIT License
Classifier: Operating System :: OS Independent
Requires-Python: >=3.6
Requires-Dist: numpy
Dynamic: author
Dynamic: classifier
Dynamic: description
Dynamic: description-content-type
Dynamic: home-page
Dynamic: requires-dist
Dynamic: requires-python
Dynamic: summary
